e3series/__init__.py
e3series/com.py
e3series/py.typed
e3series/tools.py
e3series/types.py
e3series-27.0.0.dist-info/METADATA
e3series-27.0.0.dist-info/WHEEL
e3series-27.0.0.dist-info/licenses/LICENSE
e3series-27.0.0.dist-info/RECORD
