Metadata-Version: 2.4
Name: e3series
Version: 27.0.0
Summary: Python wrapper and utilities for the E3.series COM interface.
Project-URL: Homepage, https://www.zuken.com/e3series
Project-URL: Issues, https://support.zuken.com/global/
Author-email: Zuken E3 GmbH <e3-support@de.zuken.com>
License-File: LICENSE
Keywords: CAE,E3.series,E3.series COM interface,ECAD,Electrical CAD,Electrical CAD scripting,Electrical cabinet,Electrical engineering,Formboard,Harness,Zuken
Classifier: Development Status :: 4 - Beta
Classifier: License :: OSI Approved :: MIT License
Classifier: Operating System :: Microsoft :: Windows
Classifier: Programming Language :: Python :: 3
Classifier: Topic :: Scientific/Engineering :: Electronic Design Automation (EDA)
Requires-Python: >=3.9
Requires-Dist: psutil>=5.7.3
Requires-Dist: pywin32>=306
Requires-Dist: typing-extensions>=4.13.1
